[{"nom":"Adam Baldwin","description":""},{"nom":"Adam Christian","description":""},{"nom":"Adam Solove","description":""},{"nom":"Andrew Dupont","description":""},{"nom":"Angelina Fabbro","description":""},{"nom":"Angus Croll","description":""},{"nom":"Ben Farrell","description":""},{"nom":"Blaine Bublitz","description":""},{"nom":"Brandon Dimcheff","description":""},{"nom":"Brendan Eich","description":""},{"nom":"Brian Arnold","description":""},{"nom":"Brian Cavalier","description":""},{"nom":"Brian LeRoux","description":""},{"nom":"Carter Rabasa","description":""},{"nom":"Chris Williams","description":""},{"nom":"Dan Webb","description":""},{"nom":"Daniel Tralamazza","description":""},{"nom":"Domenic Denicola","description":""},{"nom":"Erich Gamma","description":""},{"nom":"Felix Geisendörfer","description":""},{"nom":"Filip Maj & Michael Brooks","description":""},{"nom":"Garann Means","description":""},{"nom":"Janessa Det","description":""},{"nom":"Jed Schmidt","description":""},{"nom":"John Kleinschmidt","description":""},{"nom":"John-David Dalton","description":""},{"nom":"Josh Holmes","description":""},{"nom":"Justin Meyer","description":""},{"nom":"Luis Montes","description":""},{"nom":"Marcus Philips","description":""},{"nom":"Narciso (nj) Jaramillo","description":""},{"nom":"Nathan Totten","description":""},{"nom":"Nicole Sullivan","description":""},{"nom":"None","description":""},{"nom":"Nuno Job","description":""},{"nom":"Olivier Crameri","description":""},{"nom":"Pamela Fox","description":""},{"nom":"Peter Flynn","description":""},{"nom":"Peter Higgins","description":""},{"nom":"Peter van der Zee","description":""},{"nom":"Raquel Vèlez ","description":""},{"nom":"Ray Daly","description":""},{"nom":"Rebecca Murphey","description":""},{"nom":"Remy Sharp","description":""},{"nom":"Scott Andrews","description":""},{"nom":"Seb Lee-Delisle","description":""},{"nom":"Selena Deckelmann","description":""},{"nom":"Stephen Bannasch","description":""},{"nom":"Steven Wittens","description":""},{"nom":"Tomomi Imura (aka @girlie_mac)","description":""},{"nom":"YayQuery","description":""}]
